easy_datetime/__init__.py
easy_datetime-0.1.0.dist-info/METADATA
easy_datetime-0.1.0.dist-info/WHEEL
easy_datetime-0.1.0.dist-info/top_level.txt
easy_datetime-0.1.0.dist-info/RECORD
