Metadata-Version: 2.1
Name: easy_datetime
Version: 0.1.0
Summary: A simple package to automatically detect and convert datetime strings to Unix timestamps
Home-page: https://github.com/yourusername/easy_datetime
Author: Lucy
Author-email: 
License: MIT
Project-URL: Homepage, https://github.com/yourusername/easy_datetime
Classifier: Programming Language :: Python :: 3
Classifier: License :: OSI Approved :: MIT License
Classifier: Operating System :: OS Independent
Requires-Python: >=3.6
Requires-Dist: python-dateutil>=2.8.2
